{"assets":{"B3C5BF08B871D2809F63D08B33E897D3":{"type":"texture","index":0,"assetRequest":{"type":"slide","state":"contents","slide":"none"},"url":{"native":"assets\/B20016E6-F4C4-4E88-92D7-D08175879EE2.pdf"},"width":1920,"height":1080},"BB6277F673FBF073418A91FC06A0F772":{"type":"texture","index":1,"assetRequest":{"type":"slide","state":"contents","slide":"none"},"url":{"native":"assets\/B20016E6-F4C4-4E88-92D7-D08175879EE2.pdf"},"width":1920,"height":1080}},"events":[{"effects":[{"beginTime":0,"baseLayer":{"animations":[],"initialState":{"affineTransform":[1,0,0,1,0,0],"masksToBounds":false,"rotation":0,"scale":1,"position":{"pointX":960,"pointY":540},"width":1920,"sublayerTransform":[1,0,0,0,0,1,0,0,0,0,1,0,0,0,0,1],"contentsRect":{"y":0,"x":0,"width":1,"height":1},"opacity":1,"edgeAntialiasingMask":251658240,"height":1080,"hidden":false,"anchorPoint":{"pointX":0.5,"pointY":0.5}},"objectID":"0","layers":[{"animations":[],"initialState":{"affineTransform":[1,0,0,1,0,0],"masksToBounds":false,"rotation":0,"scale":1,"position":{"pointX":960,"pointY":540},"width":1920,"sublayerTransform":[1,0,0,0,0,1,0,0,0,0,1,-0.00035007912466775983,0,0,0,1],"contentsRect":{"y":0,"x":0,"width":1,"height":1},"opacity":1,"edgeAntialiasingMask":251658240,"height":1080,"hidden":false,"anchorPoint":{"pointX":0.5,"pointY":0.5}},"layers":[{"animations":[{"additive":false,"timeOffset":0,"beginTime":0,"repeatCount":0,"fillMode":"both","duration":2,"autoreverses":false,"animations":[{"repeatCount":0,"removedOnCompletion":true,"timingFunctions":[{"timingFunction":"custom","timingControlPoint1y":0.098297290503978729,"timingControlPoint2x":0.89979743957519531,"timingControlPoint1x":0.30064624547958374,"timingControlPoint2y":0.59738725423812866},{"timingFunction":"custom","timingControlPoint1y":0.87324005365371704,"timingControlPoint2x":0.70581597089767456,"timingControlPoint1x":0.45573881268501282,"timingControlPoint2y":1},{"timingFunction":"custom","timingControlPoint1y":0.098297290503978729,"timingControlPoint2x":0.89979743957519531,"timingControlPoint1x":0.30064624547958374,"timingControlPoint2y":0.59738725423812866},{"timingFunction":"custom","timingControlPoint1y":0.87324005365371704,"timingControlPoint2x":0.70581597089767456,"timingControlPoint1x":0.45573881268501282,"timingControlPoint2y":1},{"timingFunction":"custom","timingControlPoint1y":0.098297290503978729,"timingControlPoint2x":0.89979743957519531,"timingControlPoint1x":0.30064624547958374,"timingControlPoint2y":0.59738725423812866},{"timingFunction":"custom","timingControlPoint1y":0.87324005365371704,"timingControlPoint2x":0.70581597089767456,"timingControlPoint1x":0.45573881268501282,"timingControlPoint2y":1},{"timingFunction":"custom","timingControlPoint1y":0.098297290503978729,"timingControlPoint2x":0.89979743957519531,"timingControlPoint1x":0.30064624547958374,"timingControlPoint2y":0.59738725423812866},{"timingFunction":"custom","timingControlPoint1y":0.87324005365371704,"timingControlPoint2x":0.70581597089767456,"timingControlPoint1x":0.45573881268501282,"timingControlPoint2y":1},{"timingFunction":"custom","timingControlPoint1y":0.098297290503978729,"timingControlPoint2x":0.89979743957519531,"timingControlPoint1x":0.30064624547958374,"timingControlPoint2y":0.59738725423812866},{"timingFunction":"custom","timingControlPoint1y":0.87324005365371704,"timingControlPoint2x":0.70581597089767456,"timingControlPoint1x":0.45573881268501282,"timingControlPoint2y":1},{"timingFunction":"custom","timingControlPoint1y":0.098297290503978729,"timingControlPoint2x":0.89979743957519531,"timingControlPoint1x":0.30064624547958374,"timingControlPoint2y":0.59738725423812866},{"timingFunction":"custom","timingControlPoint1y":0.87324005365371704,"timingControlPoint2x":0.70581597089767456,"timingControlPoint1x":0.45573881268501282,"timingControlPoint2y":1},{"timingFunction":"custom","timingControlPoint1y":0.098297290503978729,"timingControlPoint2x":0.89979743957519531,"timingControlPoint1x":0.30064624547958374,"timingControlPoint2y":0.59738725423812866},{"timingFunction":"custom","timingControlPoint1y":0.87324005365371704,"timingControlPoint2x":0.70581597089767456,"timingControlPoint1x":0.45573881268501282,"timingControlPoint2y":1},{"timingFunction":"custom","timingControlPoint1y":0.098297290503978729,"timingControlPoint2x":0.89979743957519531,"timingControlPoint1x":0.30064624547958374,"timingControlPoint2y":0.59738725423812866},{"timingFunction":"custom","timingControlPoint1y":0.87324005365371704,"timingControlPoint2x":0.70581597089767456,"timingControlPoint1x":0.45573881268501282,"timingControlPoint2y":1},{"timingFunction":"custom","timingControlPoint1y":0.098297290503978729,"timingControlPoint2x":0.89979743957519531,"timingControlPoint1x":0.30064624547958374,"timingControlPoint2y":0.59738725423812866},{"timingFunction":"custom","timingControlPoint1y":0.87324005365371704,"timingControlPoint2x":0.70581597089767456,"timingControlPoint1x":0.45573881268501282,"timingControlPoint2y":1},{"timingFunction":"custom","timingControlPoint1y":0.098297290503978729,"timingControlPoint2x":0.89979743957519531,"timingControlPoint1x":0.30064624547958374,"timingControlPoint2y":0.59738725423812866}],"keyTimes":[0,0.13607418525566894,0.27214837051133789,0.40822255576700683,0.50401761591342553,0.59981267605984423,0.66725157735632412,0.73469047865280401,0.78216688715575733,0.82964329565871064,0.86306628033086685,0.89648926500302295,0.92001875974830671,0.94354825449359048,0.96011281712612984,0.9766773797586692,0.9883386898793346,1,1,1],"additive":false,"values":[{"scalar":-1080},{"scalar":0},{"scalar":-535.25224687806065},{"scalar":0},{"scalar":-265.2731183222337},{"scalar":0},{"scalar":-131.47040057252337},{"scalar":0},{"scalar":-65.157247504075741},{"scalar":0},{"scalar":-32.29218808050598},{"scalar":0},{"scalar":-16.004135395092362},{"scalar":0},{"scalar":-7.9317124347813763},{"scalar":0},{"scalar":-3.9309878725068379},{"scalar":0},{"scalar":-1.9482130474163819},{"scalar":0}],"timeOffset":0,"autoreverses":false,"property":"transform.translation.y","fillMode":"removed","duration":2,"beginTime":0},{"additive":false,"timeOffset":0,"beginTime":0,"from":{"scalar":1},"repeatCount":0,"fillMode":"removed","duration":2,"autoreverses":false,"property":"transform.translation.z","to":{"scalar":1},"removedOnCompletion":true}],"removedOnCompletion":false}],"layers":[],"texturedRectangle":{"isBackgroundTexture":false,"singleTextureOpacity":1,"textureType":0,"textBaseline":0,"textXHeight":0,"isVerticalText":false},"initialState":{"affineTransform":[1,0,0,1,0,0],"masksToBounds":false,"rotation":0,"scale":1,"position":{"pointX":960,"pointY":540},"width":1920,"sublayerTransform":[1,0,0,0,0,1,0,0,0,0,1,0,0,0,0,1],"contentsRect":{"y":0,"x":0,"width":1,"height":1},"opacity":1,"edgeAntialiasingMask":0,"height":1080,"hidden":false,"anchorPoint":{"pointX":0.5,"pointY":0.5}},"texture":"BB6277F673FBF073418A91FC06A0F772"},{"animations":[],"layers":[],"texturedRectangle":{"isBackgroundTexture":false,"singleTextureOpacity":1,"textureType":0,"textBaseline":0,"textXHeight":0,"isVerticalText":false},"initialState":{"affineTransform":[1,0,0,1,0,0],"masksToBounds":false,"rotation":0,"scale":1,"position":{"pointX":960,"pointY":540},"width":1920,"sublayerTransform":[1,0,0,0,0,1,0,0,0,0,1,0,0,0,0,1],"contentsRect":{"y":0,"x":0,"width":1,"height":1},"opacity":1,"edgeAntialiasingMask":0,"height":1080,"hidden":false,"anchorPoint":{"pointX":0.5,"pointY":0.5}},"texture":"B3C5BF08B871D2809F63D08B33E897D3"}]}]},"effects":[],"duration":2,"type":"transition","attributes":{"direction":0},"name":"apple:bounce","objectID":"0"}],"automaticPlay":false,"hyperlinks":[],"accessibility":[{"text":"Review Git Commands","targetRectangle":{"y":89,"x":99,"width":757.61350061366693,"height":85.904247283935547}},{"text":"git push # to push to server","targetRectangle":{"y":398.52792358398438,"x":147.00000381469727,"width":940.80000000000041,"height":63}},{"text":"git pull # to push from server","targetRectangle":{"y":455.22792208194733,"x":147.00000381469727,"width":1008.0000000000005,"height":108}},{"text":"In case of pushing new branch","targetRectangle":{"y":658.62791907787323,"x":140.14286041259766,"width":657.88799999999992,"height":100.656005859375}},{"text":"git push origin HEAD:<branch-name> ","targetRectangle":{"y":755.06231716499315,"x":147.00000381469727,"width":974.40000000000009,"height":164.69999849796295}},{"text":"Large rock formation under dark clouds with a dirt road in the foreground","targetRectangle":{"y":249.26416015625,"x":1205.6327819824219,"width":643.96354675292969,"height":665.4716739654541}},{"text":"Push - Pull","targetRectangle":{"y":190.44745779037476,"x":98.599999904632568,"width":282.09500000000003,"height":66.404617309570312}}],"baseLayer":{"animations":[],"initialState":{"affineTransform":[1,0,0,1,0,0],"masksToBounds":false,"rotation":0,"scale":1,"position":{"pointX":960,"pointY":540},"width":1920,"sublayerTransform":[1,0,0,0,0,1,0,0,0,0,1,0,0,0,0,1],"contentsRect":{"y":0,"x":0,"width":1,"height":1},"opacity":1,"edgeAntialiasingMask":251658240,"height":1080,"hidden":false,"anchorPoint":{"pointX":0.5,"pointY":0.5}},"objectID":"0","layers":[{"animations":[],"initialState":{"affineTransform":[1,0,0,1,0,0],"masksToBounds":false,"rotation":0,"scale":1,"position":{"pointX":960,"pointY":540},"width":1920,"sublayerTransform":[1,0,0,0,0,1,0,0,0,0,1,-0.00035007912466775983,0,0,0,1],"contentsRect":{"y":0,"x":0,"width":1,"height":1},"opacity":1,"edgeAntialiasingMask":251658240,"height":1080,"hidden":false,"anchorPoint":{"pointX":0.5,"pointY":0.5}},"layers":[{"animations":[],"layers":[],"texturedRectangle":{"isBackgroundTexture":false,"singleTextureOpacity":1,"textureType":0,"textBaseline":0,"textXHeight":0,"isVerticalText":false},"initialState":{"affineTransform":[1,0,0,1,0,0],"masksToBounds":false,"rotation":0,"scale":1,"position":{"pointX":960,"pointY":540},"width":1920,"sublayerTransform":[1,0,0,0,0,1,0,0,0,0,1,0,0,0,0,1],"contentsRect":{"y":0,"x":0,"width":1,"height":1},"opacity":1,"edgeAntialiasingMask":0,"height":1080,"hidden":false,"anchorPoint":{"pointX":0.5,"pointY":0.5}},"texture":"B3C5BF08B871D2809F63D08B33E897D3"}]}]}}]}